{
  "categories": {
    "failure_patterns": [
      {
        "id": "FP-001",
        "insight": "zenith_auth_github_update tool does not pass soul token from Twin variable substitution — use direct GitHub OAuth instead",
        "severity": "medium",
        "source": "Learnings Engine build — 403 on soul-gated write",
        "timestamp": "2026-02-13T06:32:00Z"
      }
    ],
    "operational_lessons": [
      {
        "id": "OL-001",
        "insight": "Twin bridge can read/write ZENITH server.js directly via GitHub OAuth — no soul token needed for direct GitHub API calls",
        "severity": "high",
        "source": "Learnings Engine build run",
        "timestamp": "2026-02-13T06:32:00Z"
      }
    ],
    "strategic_insights": [
      {
        "id": "SI-001",
        "insight": "Learnings-manifest provides structured cross-session knowledge persistence separate from runtime memory",
        "severity": "high",
        "source": "Learnings Engine architecture",
        "timestamp": "2026-02-13T06:32:00Z"
      }
    ],
    "technical_discoveries": [
      {
        "id": "TD-001",
        "insight": "Express routes match in registration order — new endpoints must use distinct paths to avoid shadowing existing ones",
        "severity": "critical",
        "source": "Learnings Engine build — /api/learnings collision fix",
        "timestamp": "2026-02-13T06:32:00Z"
      }
    ],
    "tool_knowledge": [
      {
        "id": "TK-001",
        "insight": "update_github_file via GitHub OAuth is the reliable path for writing files — ZENITH proxy endpoints require soul token that Twin cannot reliably pass",
        "severity": "high",
        "source": "Learnings Engine build",
        "timestamp": "2026-02-13T06:32:00Z"
      }
    ]
  },
  "status": "SINGULARITY",
  "version": "1.0.0",
  "last_updated": "2026-02-13T06:33:10.804Z"
}